langchain_util/__init__.py
langchain_util/chains/__init__.py
langchain_util/chains/concatenate_chain.py
langchain_util/chains/sentiment/__init__.py
langchain_util/chains/sentiment/parser.py
langchain_util/chains/sentiment/sentiment_chain.py
langchain_util/chains/sentiment/stuff_prompt.py
langchain_util/text_splitter.py
langchain_util/tools/__init__.py
langchain_util/tools/agent_as_tool.py
langchain_util-0.1.7.dist-info/METADATA
langchain_util-0.1.7.dist-info/WHEEL
langchain_util-0.1.7.dist-info/RECORD
